fastapi_export_openapi/__init__.py
fastapi_export_openapi/export_openapi.py
fastapi_export_openapi/main.py
fastapi_export_openapi-0.1.2.dist-info/entry_points.txt
fastapi_export_openapi-0.1.2.dist-info/WHEEL
fastapi_export_openapi-0.1.2.dist-info/METADATA
fastapi_export_openapi-0.1.2.dist-info/RECORD
